wordlbot/__main__.py
wordlbot/official_wordlist.json.xz
wordlbot/words.txt.xz
wordlbot-1.0.1.dist-info/METADATA
wordlbot-1.0.1.dist-info/WHEEL
wordlbot-1.0.1.dist-info/entry_points.txt
wordlbot-1.0.1.dist-info/top_level.txt
wordlbot-1.0.1.dist-info/RECORD
