Metadata-Version: 2.1
Name: wordlbot
Version: 1.0.1
Summary: A tool to help solve The New Your Times' World -game
Home-page: https://github.com/kimvais/wordlbot/
Author: Kimmo Parviainen-Jalanko
Author-email: kimvais@kimva.is
License: BSD
Platform: UNKNOWN
